Metadata-Version: 1.1
Name: html-diff-wrapper
Version: 1.0
Summary: A html diff wrapper
Home-page: https://github.com/ecreall/html_diff_wrapper/
Author: Amen Souissi
Author-email: amensouissi@ecreall.com
License: AGPLv3+
Keywords: web htmldiff diff
Platform: UNKNOWN
Classifier: Programming Language :: Python
Classifier: Programming Language :: Python :: 3.4
Classifier: Framework :: Pyramid
Classifier: Topic :: Internet :: WWW/HTTP
Classifier: Topic :: Internet :: WWW/HTTP :: WSGI :: Application
Classifier: License :: OSI Approved :: GNU Affero General Public License v3 or later (AGPLv3+)
